setup.py
build/lib/pyjulia/__init__.py
build/lib/pyjulia/pyjulia.py
pyjulia/__init__.py
pyjulia/pyjulia.py
pyjulia-0.0.6.dist-info/LICENSE
pyjulia-0.0.6.dist-info/METADATA
pyjulia-0.0.6.dist-info/WHEEL
pyjulia-0.0.6.dist-info/top_level.txt
pyjulia-0.0.6.dist-info/RECORD
