Metadata-Version: 2.1
Name: pyjulia
Version: 0.0.6
Summary: A package that allows to use Julia within Python.
Author-email: Stefan Arsic <stiefelwoods@gmail.com>
Project-URL: Homepage, https://github.com/woodyxp/Pylia
Project-URL: Bug Tracker, https://github.com/woodyxp/Pylia/issues
Classifier: Programming Language :: Python :: 3
Classifier: License :: OSI Approved :: Apache Software License
Classifier: Operating System :: OS Independent
Requires-Python: >=3.5
License-File: LICENSE
